avianinsight/__init__.py
avianinsight/main.py
avianinsight/prompts.py
avianinsight-2025.12.21175643.dist-info/METADATA
avianinsight-2025.12.21175643.dist-info/WHEEL
avianinsight-2025.12.21175643.dist-info/top_level.txt
avianinsight-2025.12.21175643.dist-info/RECORD
