Metadata-Version: 2.4
Name: avianinsight
Version: 2025.12.21175643
Summary: A new package that analyzes user-provided text descriptions of bird behaviors and returns structured insights about potential bird consciousness indicators, such as problem-solving, social interaction
Author-email: avianinsight <hi@eugene.plus>
License: MIT
Project-URL: Homepage, https://github.com/chigwell/avianinsight
Requires-Python: >=3.9
Requires-Dist: langchain-llm7>=0.0.0
Requires-Dist: llmatch-messages>=0.0.0
Requires-Dist: langchain-core>=0.3.0
